awslabs/__init__.py
awslabs/eks_mcp_server/__init__.py
awslabs/eks_mcp_server/aws_helper.py
awslabs/eks_mcp_server/cloudwatch_handler.py
awslabs/eks_mcp_server/cloudwatch_metrics_guidance_handler.py
awslabs/eks_mcp_server/consts.py
awslabs/eks_mcp_server/eks_kb_handler.py
awslabs/eks_mcp_server/eks_stack_handler.py
awslabs/eks_mcp_server/iam_handler.py
awslabs/eks_mcp_server/insights_handler.py
awslabs/eks_mcp_server/k8s_apis.py
awslabs/eks_mcp_server/k8s_client_cache.py
awslabs/eks_mcp_server/k8s_handler.py
awslabs/eks_mcp_server/logging_helper.py
awslabs/eks_mcp_server/models.py
awslabs/eks_mcp_server/server.py
awslabs/eks_mcp_server/vpc_config_handler.py
awslabs/eks_mcp_server/data/eks_cloudwatch_metrics_guidance.json
awslabs/eks_mcp_server/scripts/update_eks_cloudwatch_metrics_guidance.py
awslabs/eks_mcp_server/templates/eks-templates/eks-with-vpc.yaml
awslabs/eks_mcp_server/templates/k8s-templates/deployment.yaml
awslabs/eks_mcp_server/templates/k8s-templates/service.yaml
awslabs_eks_mcp_server-0.1.21.dist-info/METADATA
awslabs_eks_mcp_server-0.1.21.dist-info/WHEEL
awslabs_eks_mcp_server-0.1.21.dist-info/entry_points.txt
awslabs_eks_mcp_server-0.1.21.dist-info/licenses/LICENSE
awslabs_eks_mcp_server-0.1.21.dist-info/licenses/NOTICE
awslabs_eks_mcp_server-0.1.21.dist-info/RECORD
